<?xml version="1.0" encoding="utf-8"?>
<themes>
    <properties it="themes"></properties>
    <item test="h0">Все вопросы</item>
	<item test="h1">Аппендицит,осложнения аппендицита</item>
	<item test="h2">Заболевания поджелудочной железы (доброкачественные и злокачественные)</item>
	<item test="h13">Заболевания щитовидной железы (доброкачественные и злокачественные)</item>
	<item test="h3">Перитонит</item>
	<item test="h4">Брюшные грыжи и их осложнения</item>
	<item test="h5">Язвенная болезнь желудка, 12-перстной кишки и ее осложнения</item>
	<item test="h6">Заболевания прямой кишки (доброкачественные и злокачественные)</item>
	<item test="h7">Кишечная непроходимость</item>
	<item test="h8">Заболевания ободочной кишки (доброкачественные и злокачественные)</item>
	<item test="h9">Заболевания  легких (доброкачественные и злокачественные)</item>
	<item test="h10">Заболевания пищевода (доброкачественные и злокачественные)</item>
	<item test="h11">Хирургическая патология печени</item>
	<item test="h12">Заболевания желчевыводящих путей, острый и хронический холецистит, осложнения</item>
</themes>